iar_tokenizer/__init__.py
iar_tokenizer/tokenizer.py
iar_tokenizer-1.0.12.dist-info/METADATA
iar_tokenizer-1.0.12.dist-info/WHEEL
iar_tokenizer-1.0.12.dist-info/top_level.txt
iar_tokenizer-1.0.12.dist-info/RECORD
