Metadata-Version: 2.1
Name: iar-tokenizer
Version: 1.0.12
Summary: A tokenizer focused on Spanish language.
Home-page: https://pypi.org/project/iar-tokenizer/
Author: Iván Arias Rodríguez
Author-email: ivan.arias.rodriguez@gmail.com
License: Creative Commons Attribution-NonCommercial-ShareAlike 4.0 International License
Platform: UNKNOWN
Classifier: Programming Language :: Python
Classifier: Development Status :: 1 - Planning
Classifier: Intended Audience :: Science/Research
Classifier: License :: Other/Proprietary License
Classifier: Natural Language :: Spanish
Classifier: Operating System :: OS Independent
Classifier: Programming Language :: Python :: 3 :: Only
Classifier: Topic :: Scientific/Engineering
Requires-Dist: nltk
